{
  "_id": "66b4d72b94ae22fadae7e0e8",
  "type": {
    "_id": "66b4d72b9021b9e80babc012",
    "name": "write_command"
  },
  "name": "writeJudicialPensions",
  "description": "Escreve toda as pensões judiciais para os beneficios selecionados no pre-processamento que estejam ativas.",
  "main_collection": "benefits_in_payroll_process",
  "Command": {
    "updateOne": {
      "update": {
        "$set": {
          "payload": "$.$$.otp_trf_getAllJudicialPension.payload"
        }
      },
      "filter": {
        "$and": [
          {
            "payload.benefit._id": "$.$$.otp_trf_getAllJudicialPension.payload.benefit._id"
          }
        ]
      },
      "upsert": true
    }
  }
}
